serverless_sdk_schema/__init__.py
serverless_sdk_schema/py.typed
serverless_sdk_schema/schema/serverless/instrumentation/tags/v1/aws_pb2.py
serverless_sdk_schema/schema/serverless/instrumentation/tags/v1/common_pb2.py
serverless_sdk_schema/schema/serverless/instrumentation/tags/v1/error_pb2.py
serverless_sdk_schema/schema/serverless/instrumentation/tags/v1/notice_pb2.py
serverless_sdk_schema/schema/serverless/instrumentation/tags/v1/tags_pb2.py
serverless_sdk_schema/schema/serverless/instrumentation/tags/v1/warning_pb2.py
serverless_sdk_schema/schema/serverless/instrumentation/v1/dev_mode_pb2.py
serverless_sdk_schema/schema/serverless/instrumentation/v1/event_pb2.py
serverless_sdk_schema/schema/serverless/instrumentation/v1/log_pb2.py
serverless_sdk_schema/schema/serverless/instrumentation/v1/metric_pb2.py
serverless_sdk_schema/schema/serverless/instrumentation/v1/request_response_pb2.py
serverless_sdk_schema/schema/serverless/instrumentation/v1/trace_pb2.py
serverless_sdk_schema-0.2.3.dist-info/METADATA
serverless_sdk_schema-0.2.3.dist-info/WHEEL
serverless_sdk_schema-0.2.3.dist-info/top_level.txt
serverless_sdk_schema-0.2.3.dist-info/RECORD
