Metadata-Version: 2.1
Name: serverless-sdk-schema
Version: 0.2.3
Summary: The protobuf generated Serverless SDK Schema
Author: serverlessinc
Project-URL: changelog, https://github.com/serverless/console/blob/main/python/packages/sdk-schema/CHANGELOG.md
Project-URL: documentation, https://github.com/serverless/console/tree/main/python/packages/sdk-schema
Project-URL: homepage, https://www.serverless.com/console
Project-URL: repository, https://github.com/serverless/console
Classifier: Programming Language :: Python :: 3 :: Only
Classifier: Programming Language :: Python :: 3.7
Classifier: Programming Language :: Python :: 3.8
Classifier: Programming Language :: Python :: 3.9
Classifier: Programming Language :: Python :: 3.10
Classifier: Programming Language :: Python :: 3.11
Requires-Python: >=3.7
Requires-Dist: protobuf (>=4.22)
Requires-Dist: typing-extensions (>=4.4)
Provides-Extra: tests
Requires-Dist: black (>=22.12) ; extra == 'tests'
Requires-Dist: pytest (>=7.2) ; extra == 'tests'
Requires-Dist: ruff (>=0.0.199) ; extra == 'tests'
